odoo8_addon_document_page_partner_id-8.0.1.0.0.99.dev17-py2.7-nspkg.pth
odoo8_addon_document_page_partner_id-8.0.1.0.0.99.dev17.dist-info/METADATA
odoo8_addon_document_page_partner_id-8.0.1.0.0.99.dev17.dist-info/RECORD
odoo8_addon_document_page_partner_id-8.0.1.0.0.99.dev17.dist-info/WHEEL
odoo8_addon_document_page_partner_id-8.0.1.0.0.99.dev17.dist-info/namespace_packages.txt
odoo8_addon_document_page_partner_id-8.0.1.0.0.99.dev17.dist-info/top_level.txt
odoo_addons/document_page_partner_id/README.rst
odoo_addons/document_page_partner_id/__init__.py
odoo_addons/document_page_partner_id/__openerp__.py
odoo_addons/document_page_partner_id/i18n/am.po
odoo_addons/document_page_partner_id/i18n/ar.po
odoo_addons/document_page_partner_id/i18n/bg.po
odoo_addons/document_page_partner_id/i18n/bs.po
odoo_addons/document_page_partner_id/i18n/ca.po
odoo_addons/document_page_partner_id/i18n/cs.po
odoo_addons/document_page_partner_id/i18n/da.po
odoo_addons/document_page_partner_id/i18n/de.po
odoo_addons/document_page_partner_id/i18n/el_GR.po
odoo_addons/document_page_partner_id/i18n/en_GB.po
odoo_addons/document_page_partner_id/i18n/es.po
odoo_addons/document_page_partner_id/i18n/es_AR.po
odoo_addons/document_page_partner_id/i18n/es_CR.po
odoo_addons/document_page_partner_id/i18n/es_EC.po
odoo_addons/document_page_partner_id/i18n/es_MX.po
odoo_addons/document_page_partner_id/i18n/es_VE.po
odoo_addons/document_page_partner_id/i18n/et.po
odoo_addons/document_page_partner_id/i18n/eu.po
odoo_addons/document_page_partner_id/i18n/fi.po
odoo_addons/document_page_partner_id/i18n/fr.po
odoo_addons/document_page_partner_id/i18n/fr_CA.po
odoo_addons/document_page_partner_id/i18n/fr_CH.po
odoo_addons/document_page_partner_id/i18n/gl.po
odoo_addons/document_page_partner_id/i18n/hr.po
odoo_addons/document_page_partner_id/i18n/hr_HR.po
odoo_addons/document_page_partner_id/i18n/hu.po
odoo_addons/document_page_partner_id/i18n/id.po
odoo_addons/document_page_partner_id/i18n/it.po
odoo_addons/document_page_partner_id/i18n/ja.po
odoo_addons/document_page_partner_id/i18n/lt.po
odoo_addons/document_page_partner_id/i18n/lv.po
odoo_addons/document_page_partner_id/i18n/mk.po
odoo_addons/document_page_partner_id/i18n/mn.po
odoo_addons/document_page_partner_id/i18n/nb.po
odoo_addons/document_page_partner_id/i18n/nb_NO.po
