Metadata-Version: 2.1
Name: odoo8-addon-document-page-partner-id
Version: 8.0.1.0.0.99.dev17
Summary: Allows to link doucment pages to a partner
Home-page: UNKNOWN
Author: Therp BV,Odoo Community Association (OCA)
Author-email: support@odoo-community.org
License: AGPL-3
Platform: UNKNOWN
Classifier: Programming Language :: Python
Classifier: Framework :: Odoo
Classifier: License :: OSI Approved :: GNU Affero General Public License v3
Requires-Python: ~=2.7
Requires-Dist: odoo8-addon-document-page
Requires-Dist: odoo (<9.0a,>=8.0a)
